tests/__init__.py
tests/test_xray_config.py
xray_configurator/__init__.py
xray_configurator/xray_configurator.py
xrayconfigurator-0.0.32.dist-info/METADATA
xrayconfigurator-0.0.32.dist-info/WHEEL
xrayconfigurator-0.0.32.dist-info/top_level.txt
xrayconfigurator-0.0.32.dist-info/RECORD
